hashprep/__init__.py
hashprep/checks/__init__.py
hashprep/checks/columns.py
hashprep/checks/core.py
hashprep/checks/correlations.py
hashprep/checks/discretizer.py
hashprep/checks/drift.py
hashprep/checks/imbalance.py
hashprep/checks/leakage.py
hashprep/checks/missing_values.py
hashprep/checks/outliers.py
hashprep/core/analyzer.py
hashprep/core/visualizations.py
hashprep/interfaces/cli/__init__.py
hashprep/interfaces/cli/main.py
hashprep/preparers/codegen.py
hashprep/preparers/suggestions.py
hashprep/reports/__init__.py
hashprep/reports/generators.py
hashprep/reports/html.py
hashprep/reports/json.py
hashprep/reports/markdown.py
hashprep/reports/pdf.py
hashprep/summaries/__init__.py
hashprep/summaries/dataset.py
hashprep/summaries/interactions.py
hashprep/summaries/missing.py
hashprep/summaries/variables.py
hashprep/utils/type_inference.py
hashprep-0.1.0a4.dist-info/licenses/LICENSE
hashprep-0.1.0a4.dist-info/METADATA
hashprep-0.1.0a4.dist-info/WHEEL
hashprep-0.1.0a4.dist-info/entry_points.txt
hashprep-0.1.0a4.dist-info/top_level.txt
hashprep-0.1.0a4.dist-info/RECORD
