Metadata-Version: 2.4
Name: hashprep
Version: 0.1.0a4
Summary: A library for dataset quality checks, preprocessing, and report generation
Author-email: "Aftaab Siddiqui (MaskedSyntax)" <aftaab@aftaab.xyz>
License: MIT License
Project-URL: Homepage, https://github.com/cachevector/hashprep
Project-URL: Repository, https://github.com/cachevector/hashprep
Project-URL: Documentation, https://github.com/cachevector/hashprep
Project-URL: Issues, https://github.com/cachevector/hashprep/issues
Requires-Python: >=3.10
License-File: LICENSE
Requires-Dist: click>=8.3.0
Requires-Dist: fastapi>=0.116.1
Requires-Dist: jinja2>=3.1.6
Requires-Dist: matplotlib>=3.10.6
Requires-Dist: numpy>=2.2.6
Requires-Dist: pandas>=2.3.2
Requires-Dist: pyyaml>=6.0.2
Requires-Dist: scikit-learn>=1.7.2
Requires-Dist: scipy>=1.15.3
Requires-Dist: seaborn>=0.13.2
Requires-Dist: starlette>=0.49.1
Requires-Dist: brotli>=1.2.0
Requires-Dist: fonttools>=4.60.2
Requires-Dist: tabulate>=0.9.0
Requires-Dist: weasyprint>=66.0
Dynamic: license-file
